{
	"@context": ["http://www.w3.org/ns/csvw"],
	"tables": {
		"url": ["90340_Data.csv"],
		"tableSchema": {
			"columns": [
				{
					"name": "Zeitraum",
					"titles": "Zeitraum",
					"datatype": "string",
					"description": "Zeitraum, für den die angegebenen Zahlen gelten. Angabe in Jahren unserer Zeitrechnung."
				},
				{
					"name": "Grossbasel",
					"titles": "Grossbasel",
					"datatype": "number",
					"description": "Zunahme der Bevölkerungszahl im Grossbasel im angegebenen Zeitraum, Angaben in Prozent"
				},
				{
					"name": "Kleinbasel",
					"titles": "Kleinbasel",
					"datatype": "number",
					"description": "Zunahme der Bevölkerungszahl im Kleinbasel im angegebenen Zeitraum, Angaben in Prozent"
				}
			],
			"mediaID": ["m90340_3"],
			"isPartOf": {
				"ObjectID": ["abb90340"],
				"volume": [
					"Kury, Patrick (Hg.): Die beschleunigte Stadt. 1856–1914. Basel 2024 (Stadt.Geschichte.Basel 6)."
				]
			},
			"title": ["Prozentuales Bevölkerungswachstum in Gross- und Kleinbasel, 1860–1910"],
			"description": [
				"Innerhalb eines halben Jahrhunderts wuchs die Bevölkerung der Stadt von 37 915 um beinahe 100 000 Einwohnerinnen und Einwohner. Während sich in Grossbasel die Bevölkerung verdreifachte, entsprach die Zunahme im Kleinbasel von 10 283 auf 48 455 Einwohnerinnen und Einwohner nahezu einer Verfünffachung. Die Einwohner:innen Kleinhüningens werden ab 1900 dem Kleinbasel zugerechnet"
			],
			"creator": [
				{
					"name": ["Franziska Schürch"]
				},
				{
					"name": ["Isabel Koellreuter"]
				}
			],
			"contributor": [
				{
					"name": ["Nico Görlich"],
					"orcid": ["0000-0003-3860-1488"]
				},
				{
					"name": ["Moritz Twente"],
					"email": ["moritz.twente@unibas.ch"],
					"orcid": ["0009-0005-7187-9774"]
				}
			],
			"publisher": ["Stadt.Geschichte.Basel"],
			"date": ["1860/1910"],
			"temporal": [["19. Jahrhundert"], ["20. Jahrhundert"]],
			"type": ["Dataset"],
			"format": ["text/csv"],
			"source": [
				"Quelle: Bauer, Stephan: Die Bevölkerung des Kantons Basel-Stadt, Basel 1905; Jenny, Oskar Hugo: Die Bevölkerung des Kantons Basel-Stadt. Am 1. Dezember 1910, Basel 1924 (Mitteilungen des Statistischen Amtes des Kantons Basel-Stadt Nr. 28, Ed. 1924)., Tabelle I, 3*–5*. Bearbeitung: Nico Görlich / Moritz Twente"
			],
			"language": ["de"],
			"relation": [["m90340_1"], ["m90340_2"]],
			"rights": ["Public Domain Mark"],
			"license": ["https://creativecommons.org/public-domain/pdm/"],
			"modified": ["2025-06-26 15:25:43"],
			"bibliographicCitation": [
				"Stadt.Geschichte.Basel: Prozentuales Bevölkerungswachstum in Gross- und Kleinbasel, 1860–1910. Forschungsdatenplattform Stadt.Geschichte.Basel, <https://forschung.stadtgeschichtebasel.ch/items/abb90340.html#m90340_3>, letzte Aktualisierung: 26.06.2025."
			]
		}
	}
}
